CHANGES.txt
DEPENDENCES.txt
README.txt
TODO.txt
setup.py
design/neuralskin.png
src/ng/__init__.py
src/ng.skin.neural.egg-info/PKG-INFO
src/ng.skin.neural.egg-info/SOURCES.txt
src/ng.skin.neural.egg-info/dependency_links.txt
src/ng.skin.neural.egg-info/namespace_packages.txt
src/ng.skin.neural.egg-info/not-zip-safe
src/ng.skin.neural.egg-info/requires.txt
src/ng.skin.neural.egg-info/top_level.txt
src/ng/skin/__init__.py
src/ng/skin/neural/__init__.py
src/ng/skin/neural/configure.zcml
src/ng/skin/neural/interfaces.py
src/ng/skin/neural/ng.skin.neural.txt
src/ng/skin/neural/skeleton.pt
src/ng/skin/neural/style.css
src/ng/skin/neural/style_ie.css
src/ng/skin/neural/etc/ng.skin.neural-configure.zcml
src/ng/skin/neural/images/bottomlogo.png
src/ng/skin/neural/images/logo.gif
src/ng/skin/neural/images/toplogo.png
src/ng/skin/neural/main/__init__.py
src/ng/skin/neural/main/configure.zcml
src/ng/skin/neural/main/main.css
src/ng/skin/neural/main/main.pt