Metadata-Version: 1.0
Name: ng.skin.neural
Version: 2.0.2
Summary: Redesigned old neural.ru skin for ng.site.content
Home-page: http://www.dreambot.ru/dreambotzope3releases/ng.skin.neural
Author: Andrey Orlov
Author-email: dbdt@dreambot.ru
License: GPL v2.1
Platform: UNKNOWN
Classifier: Environment :: Web Environment
Classifier: Intended Audience :: Developers
Classifier: License :: OSI Approved :: GNU General Public License (GPL)
Classifier: Programming Language :: Python
Classifier: Operating System :: OS Independent
Classifier: Topic :: Internet :: WWW/HTTP
Classifier: Framework :: Zope3
